superleap/__init__.py
superleap/__main__.py
superleap/audit_data.py
superleap/client.py
superleap/common.py
superleap-0.1.3.dist-info/METADATA
superleap-0.1.3.dist-info/WHEEL
superleap-0.1.3.dist-info/licenses/LICENSE
superleap-0.1.3.dist-info/RECORD
