Metadata-Version: 2.4
Name: superleap
Version: 0.1.3
Summary: A Python client for Superleap API
Project-URL: Repository, https://github.com/superleapai/python-sdk
Author-email: Cariappa K Ganapathi <cariappa@superleap.com>
License: MIT License
License-File: LICENSE
Classifier: Development Status :: 3 - Alpha
Classifier: Intended Audience :: Developers
Classifier: Programming Language :: Python :: 3
Classifier: Programming Language :: Python :: 3.9
Requires-Python: >=3.8
Requires-Dist: ratelimit>=2.2.1
Requires-Dist: requests>=2.28.0
Provides-Extra: dev
Requires-Dist: black; extra == 'dev'
Requires-Dist: build; extra == 'dev'
Requires-Dist: flake8; extra == 'dev'
Requires-Dist: isort; extra == 'dev'
Requires-Dist: mypy; extra == 'dev'
Requires-Dist: pytest-cov; extra == 'dev'
Requires-Dist: pytest>=7.0; extra == 'dev'
Requires-Dist: twine; extra == 'dev'
